pymodaq_plugins_femto/VERSION
pymodaq_plugins_femto/__init__.py
pymodaq_plugins_femto/daq_move_plugins/__init__.py
pymodaq_plugins_femto/daq_move_plugins/daq_move_Delay.py
pymodaq_plugins_femto/daq_move_plugins/daq_move_DelayStage.py
pymodaq_plugins_femto/daq_move_plugins/daq_move_GlassInsertion.py
pymodaq_plugins_femto/daq_move_plugins/daq_move_WedgeInsertion.py
pymodaq_plugins_femto/daq_viewer_plugins/__init__.py
pymodaq_plugins_femto/daq_viewer_plugins/plugins_0D/__init__.py
pymodaq_plugins_femto/daq_viewer_plugins/plugins_1D/__init__.py
pymodaq_plugins_femto/daq_viewer_plugins/plugins_1D/daq_1Dviewer_Femto.py
pymodaq_plugins_femto/daq_viewer_plugins/plugins_2D/__init__.py
pymodaq_plugins_femto/daq_viewer_plugins/plugins_ND/__init__.py
pymodaq_plugins_femto/data/spectral_data.csv
pymodaq_plugins_femto/hardware/__init__.py
pymodaq_plugins_femto-0.1.0.dist-info/LICENSE
pymodaq_plugins_femto-0.1.0.dist-info/METADATA
pymodaq_plugins_femto-0.1.0.dist-info/WHEEL
pymodaq_plugins_femto-0.1.0.dist-info/entry_points.txt
pymodaq_plugins_femto-0.1.0.dist-info/top_level.txt
pymodaq_plugins_femto-0.1.0.dist-info/RECORD
