Metadata-Version: 2.1
Name: pymodaq-plugins-femto
Version: 0.1.0
Summary: Plugin to simulate acquisition from ultrashort pulse measurement device based on the pypret package
Home-page: https://github.com/CEMES-CNRS/pymodaq_plugins_femto
Author: Sébastien Weber
Author-email: sebastien.weber@cemes.fr
License: MIT
Platform: UNKNOWN
Classifier: Programming Language :: Python :: 3
Classifier: Development Status :: 5 - Production/Stable
Classifier: Environment :: Other Environment
Classifier: Intended Audience :: Science/Research
Classifier: Topic :: Scientific/Engineering :: Human Machine Interfaces
Classifier: Topic :: Scientific/Engineering :: Visualization
Classifier: License :: OSI Approved :: MIT License
Classifier: Operating System :: OS Independent
Classifier: Topic :: Software Development :: Libraries :: Python Modules
Classifier: Topic :: Software Development :: User Interfaces
License-File: LICENSE
Requires-Dist: toml
Requires-Dist: pypret
Requires-Dist: pymodaq-femto
